prestodb/__init__.py
prestodb/auth.py
prestodb/client.py
prestodb/constants.py
prestodb/dbapi.py
prestodb/exceptions.py
prestodb/redirect.py
prestodb/transaction.py
presto_python_client-0.8.4.dist-info/LICENSE
presto_python_client-0.8.4.dist-info/METADATA
presto_python_client-0.8.4.dist-info/WHEEL
presto_python_client-0.8.4.dist-info/top_level.txt
presto_python_client-0.8.4.dist-info/RECORD
